evalit/__init__.py
evalit/_legacy/webui_v0/README.md
evalit/_legacy/webui_v0/__init__.py
evalit/_legacy/webui_v0/webui_base_client.py
evalit/_legacy/webui_v0/webui_t2i_client.py
evalit/_legacy/webui_v0/webui_test_driver.py
evalit/_legacy/webui_v0/webui_xyz_args.py
evalit/cli.py
evalit/local/__init__.py
evalit/local/mini_eval_gui.py
evalit/webui/README.md
evalit/webui/__init__.py
evalit/webui/img_grid_maker.py
evalit/webui/webui_options_manager.py
evalit/webui/webui_t2i_client.py
evalit-0.2.dist-info/METADATA
evalit-0.2.dist-info/WHEEL
evalit-0.2.dist-info/entry_points.txt
evalit-0.2.dist-info/RECORD
