Metadata-Version: 2.1
Name: evalit
Version: 0.2
Summary: Eval-it Evaluates models for Training
Author: yada
Author-email: trojblue@gmail.com
Requires-Python: >=3.10,<4.0
Classifier: Programming Language :: Python :: 3
Classifier: Programming Language :: Python :: 3.10
Classifier: Programming Language :: Python :: 3.11
Requires-Dist: pillow (>=10.0.0,<11.0.0)
Requires-Dist: pyperclip (>=1.8.2,<2.0.0)
Requires-Dist: pysimplegui (>=4.60.5,<5.0.0)
Requires-Dist: tqdm (>=4.65.0,<5.0.0)
Requires-Dist: unibox (>=0.3.0,<0.4.0)
Requires-Dist: webuiapi (>=0.9.5,<0.10.0)
